[
  {
    "id": 1,
    "topic": ["网页文件中，能起到动画效果的图形格式是_____。"],
    "options": [
      {
        "label": "GIF",
        "isTrue": true
      },
      {
        "label": "JPEG"
      },
      {
        "label": "TIF"
      },
      {
        "label": "BMP"
      }
    ]
  },
  {
    "id": 2,
    "topic": ["实现鼠标经过图像应选两幅_____的图片。"],
    "options": [
      {
        "label": "大小一样",
        "isTrue": true
      },
      {
        "label": "相差一倍"
      },
      {
        "label": "相差两倍"
      },
      {
        "label": "相差三倍"
      }
    ]
  },
  {
    "id": 3,
    "topic": [
      "在设置图像超链接时，可以在“替代”文本框中填入注释的文字，下面不是其作用是_____。"
    ],
    "options": [
      {
        "label": "每过段时间图像上都会定时显示注释的文字",
        "isTrue": true
      },
      {
        "label": "当浏览器不支持图像时，使用文字替换图像"
      },
      {
        "label": "当鼠标移到图像并停留一段时间后，这些注释文字将显示出来"
      },
      {
        "label": "在浏览者关闭图像显示功能时，使用文字替换图像"
      }
    ]
  },
  {
    "id": 4,
    "topic": ["在Dreamweaver中，下面_____对象可以添加热点。"],
    "options": [
      {
        "label": "图像",
        "isTrue": true
      },
      {
        "label": "帧"
      },
      {
        "label": "文字"
      },
      {
        "label": "任何对象"
      }
    ]
  },
  {
    "id": 5,
    "topic": ["图像映射上的热点区域不可以是以下_____形状。"],
    "options": [
      {
        "label": "心形",
        "isTrue": true
      },
      {
        "label": "矩形"
      },
      {
        "label": "椭圆形"
      },
      {
        "label": "多边形"
      }
    ]
  },
  {
    "id": 6,
    "topic": ["_____是网页与网页之间联系的纽带，也是网页的重要特色。"],
    "options": [
      {
        "label": "超链接",
        "isTrue": true
      },
      {
        "label": "框架"
      },
      {
        "label": "表格"
      },
      {
        "label": "图像"
      }
    ]
  },
  {
    "id": 7,
    "topic": [
      "使用链接时，若想在一个新窗口打开被链接的文档，应在属性面板的目标下拉菜单中选择_____。"
    ],
    "options": [
      {
        "label": "_blank",
        "isTrue": true
      },
      {
        "label": "_parent"
      },
      {
        "label": "_self"
      },
      {
        "label": "_top"
      }
    ]
  },
  {
    "id": 8,
    "topic": ["在图片中设置超链接的说法中正确的是_____。"],
    "options": [
      {
        "label": "一个图片上能设置多个超连接",
        "isTrue": true
      },
      {
        "label": "图片上不能设置超连接"
      },
      {
        "label": "一个图片上只能设置一个超连接"
      },
      {
        "label": "鼠标移动到带超连接的图片上仍然显示箭头形状"
      }
    ]
  },
  {
    "id": 9,
    "topic": ["如果要实现页面上有跳转到页面首行的链接，应通过_____来设置。"],
    "options": [
      {
        "label": "锚点链接",
        "isTrue": true
      },
      {
        "label": "表单"
      },
      {
        "label": "表格"
      },
      {
        "label": "外部链接"
      }
    ]
  },
  {
    "id": 10,
    "topic": ["关于在网页中加入命名锚点来实现跳转的说法，不正确的是_____。"],
    "options": [
      {
        "label": "只能跳转到其它页面的页首",
        "isTrue": true
      },
      {
        "label": "在页面编辑时，需要使用“插入”面板中的“命名锚记”"
      },
      {
        "label": "可以实现同一页面中不同位置的跳转"
      },
      {
        "label": "可以实现页面间的跳转"
      }
    ]
  },
  {
    "id": 11,
    "topic": ["下面有关超链接的描述正确的是_____。"],
    "options": [
      {
        "label": "可以建立一个空链接，只需在链接中输入“＃”即可",
        "isTrue": true
      },
      {
        "label": "如果不设置目标属性，则默认为_blank"
      },
      {
        "label": "目标属性中值的个数是不会发生变化的"
      },
      {
        "label": "如果要链接到“新浪网”，那么只需在链接中输入“sina.com.cn”即可"
      }
    ]
  },
  {
    "id": 12,
    "topic": ["在Dreamweaver中，下列关于创建超链接的叙述错误的是_____。"],
    "options": [
      {
        "label": "不能与外部网站链接",
        "isTrue": true
      },
      {
        "label": "一张图片可以包含多个链接"
      },
      {
        "label": "可以链接到电子邮件信箱"
      },
      {
        "label": "在表单中可以建立超链接"
      }
    ]
  },
  {
    "id": 13,
    "topic": [
      "在Dreamweaver中，若想在指定的窗口或框架打开指定的网页，可使用_____行为实现。"
    ],
    "options": [
      {
        "label": "转到URL",
        "isTrue": true
      },
      {
        "label": "弹出信息"
      },
      {
        "label": "改变属性"
      },
      {
        "label": "打开浏览器窗口"
      }
    ]
  },
  {
    "id": 14,
    "topic": ["在HTML中，下面_____是超链接标签"],
    "options": [
      {
        "label": "<a>…<a>",
        "isTrue": true
      },
      {
        "label": "〈IMG〉…〈/IMG〉"
      },
      {
        "label": "〈FONT〉…〈/FONT〉"
      },
      {
        "label": "〈P〉…〈/P〉"
      }
    ]
  },
  {
    "id": 15,
    "topic": ["设置链接颜色使用哪种标记_____。"],
    "options": [
      {
        "label": "<body link=？>",
        "isTrue": true
      },
      {
        "label": "<body text=？>"
      },
      {
        "label": "<body bgcolor=？>"
      },
      {
        "label": "<body align=？>"
      }
    ]
  },
  {
    "id": 16,
    "topic": ["指明链接的对象使用的参数是_____。"],
    "options": [
      {
        "label": "img"
      },
      {
        "label": "font"
      },
      {
        "label": "href",
        "isTrue": true
      },
      {
        "label": "src"
      }
    ]
  },
  {
    "id": 17,
    "topic": ["html 语言中，创建一个自动发送电子的超链接的标记是_____。"],
    "options": [
      {
        "label": "<a href=\"mailto:EMAIL\"></herf>"
      },
      {
        "label": "<href=\"mailto:EMAIL\">"
      },
      {
        "label": "<href=\"mailto:EMAIL\"></herf>"
      },
      {
        "label": "<a href=\"mailto:EMAIL\"></a>",
        "isTrue": true
      }
    ]
  },
  {
    "id": 18,
    "topic": [
      "如果要使一个网站的风格统一并便于更新，在使用 CSS 文件的时候，最好是使用_____。"
    ],
    "options": [
      {
        "label": "内嵌式样式表"
      },
      {
        "label": "外部链接样式表",
        "isTrue": true
      },
      {
        "label": "局部应用样式表"
      },
      {
        "label": "以上三种都一样"
      }
    ]
  },
  {
    "id": 19,
    "topic": ["热点链接的实质是_____。"],
    "options": [
      {
        "label": "图片上的一块区域成为一个链接。",
        "isTrue": true
      },
      {
        "label": "在图片的一块区域上绘制一个层，为层制作链接。"
      },
      {
        "label": "在图片上绘制位置固定的一个层，为层制作链接。"
      },
      {
        "label": "以上说法都不正确"
      }
    ]
  },
  {
    "id": 20,
    "topic": [
      "在Dreamweaver中，超级链接标签具有不同的状态，下面不属于标签状态的是_____。"
    ],
    "options": [
      {
        "label": "a：active"
      },
      {
        "label": "a：hover"
      },
      {
        "label": "a：link"
      },
      {
        "label": "a：unvisited",
        "isTrue": true
      }
    ]
  },
  {
    "id": 21,
    "topic": [
      "将链接的目标文件载入该链接所在的同一窗口中，链接的“目标”属性应设置成_____。"
    ],
    "options": [
      {
        "label": "_blank"
      },
      {
        "label": "_parent"
      },
      {
        "label": "_self",
        "isTrue": true
      },
      {
        "label": "_top"
      }
    ]
  },
  {
    "id": 22,
    "topic": [
      "如果页面内容很多，通过_____设置，浏览者只需单击目录中相应的项目就可以跳转到网页上对应的位置。"
    ],
    "options": [
      {
        "label": "电子邮件链接"
      },
      {
        "label": "表单"
      },
      {
        "label": "锚点链接",
        "isTrue": true
      },
      {
        "label": "外部链接"
      }
    ]
  },
  {
    "id": 23,
    "topic": ["在Dreamweaver MX中，下面哪个对象可以添加热点链接_____。"],
    "options": [
      {
        "label": "帧"
      },
      {
        "label": "文字"
      },
      {
        "label": "图像",
        "isTrue": true
      },
      {
        "label": "任何对象"
      }
    ]
  },
  {
    "id": 24,
    "topic": [
      "CSS选择器样式主要用于链接效果的定义，其中a:visited的作用是_____。"
    ],
    "options": [
      {
        "label": "设定正常状态下链接文字的样式"
      },
      {
        "label": "设定当前被激活链接（即在链接上按下鼠标左键时）的效果"
      },
      {
        "label": "设定访问过的链接效果",
        "isTrue": true
      },
      {
        "label": "设定当鼠标放在链接上时的文字效果"
      }
    ]
  },
  {
    "id": 25,
    "topic": [
      "在Dreamweaver CS6中，可以为图像创建热点，下面哪些热点属性不可以进行设置_____。"
    ],
    "options": [
      {
        "label": "热点的形状"
      },
      {
        "label": "热点的位置"
      },
      {
        "label": "热点的大小"
      },
      {
        "label": "热点区鼠标的灵敏程度",
        "isTrue": true
      }
    ]
  },
  {
    "id": 26,
    "topic": [
      "在设置图像超链接时，可以在alt文本框中填入注释的文字，下面不是其作用的是_____。"
    ],
    "options": [
      {
        "label": "当浏览器不支持的图像时，使用文字代替图像"
      },
      {
        "label": "当鼠标移到图像并停留一段时间后，这些注释文字将显示出来"
      },
      {
        "label": "在浏览者关闭图像显示功能时，使用文字代替图像"
      },
      {
        "label": "每过一段时间图像上都会定时显示注释文字",
        "isTrue": true
      }
    ]
  },
  {
    "id": 27,
    "topic": ["在Dreamweaver CS6中，为图像建立热点，热点形状可以为_____。"],
    "options": [
      {
        "label": "圆形"
      },
      {
        "label": "正方形"
      },
      {
        "label": "多边形"
      },
      {
        "label": "以上都是",
        "isTrue": true
      }
    ]
  },
  {
    "id": 28,
    "topic": ["在默认情况下，下面关于给文字插入超链接说法正确的是_____。"],
    "options": [
      {
        "label": "插入超链接后会发现文字已经变成蓝色，并且下面出现下划线",
        "isTrue": true
      },
      {
        "label": "只能对文字进行超链接"
      },
      {
        "label": "插入超链接后悔发现文字已经变成蓝色，但是不会出现下划线"
      },
      {
        "label": "以上说法都错误"
      }
    ]
  },
  {
    "id": 29,
    "topic": ["在Dreamweaver CS6中，有几种方式的链接目标_____。"],
    "options": [
      {
        "label": "1"
      },
      {
        "label": "2"
      },
      {
        "label": "3"
      },
      {
        "label": "4",
        "isTrue": true
      }
    ]
  },
  {
    "id": 30,
    "topic": ["关于超链接的说法正确的一项是_____。"],
    "options": [
      {
        "label": "一个超链接是由被指向的目标和指向目标的链指针组成"
      },
      {
        "label": "超链接只能是文本内容"
      },
      {
        "label": "超链接的目标可以是不同网址，同一文件的不同部分，多媒体信息，但不能是应用程序",
        "isTrue": true
      },
      {
        "label": "当单击超链接时，浏览器将下载web地址"
      }
    ]
  },
  {
    "id": 31,
    "topic": ["关于绝对路径的使用，以下说法错误的是_____。"],
    "options": [
      {
        "label": "绝对路径是指包括服务器规范在内的完全路径，通常使用http:// 来表示"
      },
      {
        "label": "绝对路径不管源文件在什么位置都可以非常精确地找到"
      },
      {
        "label": "如果希望链接其它站点上的内容，就必须使用绝对路径"
      },
      {
        "label": "使用绝对路径的链接不能链接本站点的文件，要链接本站点文件只能使用相对路径",
        "isTrue": true
      }
    ]
  },
  {
    "id": 32,
    "topic": ["在Dreamweaver中，下面对文本和图像设置超链接说法错误的是_____。"],
    "options": [
      {
        "label": "中要设置成超级链接的文字或图像，然后在属性面板的链接栏中添入相应的URL地址即可"
      },
      {
        "label": "性面板的链接栏中添入相应的URL地址格式可以是\"www.ceac.org.cn\"",
        "isTrue": true
      },
      {
        "label": "置好，后在编辑窗口中的空白处单击，可以发现选中的文本变为蓝色，并出现下划线。"
      },
      {
        "label": "置超链接方法不止一种"
      }
    ]
  },
  {
    "id": 33,
    "topic": ["下列关于热区的使用，说法不正确的是_____。"],
    "options": [
      {
        "label": "用矩形热区工具．椭圆形热区工具和多边形热区工具，分别可以创建不同形状的热区"
      },
      {
        "label": "区一旦创建之后，便无法再修改其形状，必须删除后重新创建",
        "isTrue": true
      },
      {
        "label": "中热区之后，可在属性面板中为其设置链接"
      },
      {
        "label": "用热区工具可以为一张图片设置多个链接"
      }
    ]
  }
]
